{
    "QuickSearch": {
        "QuickSearchText": "",
        "DisplayAction": "ShowRowAndHighlightCell"
    },
    "FlashingCell": {
        "FlashingCells": [
            {
                "IsLive": true,
                "ColumnName": "pnl",
                "FlashingCellDuration": 500,
                "UpColor": "#008000",
                "DownColor": "#FF0000"
            },
            {
                "IsLive": true,
                "ColumnName": "currentPrice",
                "FlashingCellDuration": 500,
                "UpColor": "#008000",
                "DownColor": "#FF0000"
            },
            {
                "IsLive": true,
                "ColumnName": "position",
                "FlashingCellDuration":500,
                "UpColor": "#008000",
                "DownColor": "#FF0000"
            }
        ]
    }
}